pylastfm/__init__.py
pylastfm/_version.py
pylastfm/auth.py
pylastfm/client.py
pylastfm/constants.py
pylastfm/error.py
pylastfm/util.py
pylastfm/api/__init__.py
pylastfm/api/album.py
pylastfm/api/api.py
pylastfm/api/artist.py
pylastfm/api/auth.py
pylastfm/api/chart.py
pylastfm/api/geo.py
pylastfm/api/library.py
pylastfm/api/tag.py
pylastfm/api/track.py
pylastfm/api/user.py
pylastfm/response/__init__.py
pylastfm/response/album.py
pylastfm/response/artist.py
pylastfm/response/chart.py
pylastfm/response/common.py
pylastfm/response/geo.py
pylastfm/response/library.py
pylastfm/response/track.py
pylastfm/response/user.py
pylastfm-0.2.0.dist-info/DESCRIPTION.rst
pylastfm-0.2.0.dist-info/METADATA
pylastfm-0.2.0.dist-info/metadata.json
pylastfm-0.2.0.dist-info/RECORD
pylastfm-0.2.0.dist-info/top_level.txt
pylastfm-0.2.0.dist-info/WHEEL
